LICENSE.txt
README.md
setup.cfg
setup.py
ncRNAFinder/Pipeline.py
ncRNAFinder/RNAcentral2.py
ncRNAFinder/Rfam.py
ncRNAFinder/__init__.py
ncRNAFinder/arrumaFastaV2.py
ncRNAFinder/ncRNAFinder.py
ncRNAFinder.egg-info/PKG-INFO
ncRNAFinder.egg-info/SOURCES.txt
ncRNAFinder.egg-info/dependency_links.txt
ncRNAFinder.egg-info/top_level.txt