Metadata-Version: 2.1
Name: ncRNAFinder
Version: 0.0.5
Summary: ncRNAfinder is an automatic and scalable system for large-scale data annotation analysis of ncRNAs which use both sequence and structural search strategy for ncRNA annotation.
Home-page: https://github.com/user/reponame
Download-URL: https://github.com/GregorioVitor/ncRNAfinder/archive/refs/tags/v_01.tar.gz
Author: gregoriovitor
Author-email: vitor-gregorio@hotmail.com
License: GPL
Keywords: ncRNA,annotation,BLAST,INFERNAL,structure
Classifier: Development Status :: 3 - Alpha
Classifier: Intended Audience :: Developers
Classifier: Topic :: Software Development :: Build Tools
Classifier: License :: OSI Approved :: MIT License
Classifier: Programming Language :: Python :: 3
Classifier: Programming Language :: Python :: 3.4
Classifier: Programming Language :: Python :: 3.5
Classifier: Programming Language :: Python :: 3.6
License-File: LICENSE.txt
